{
    "761": "190 (W201)",
    "1642": "A-Класс",
    "5878": "A-Класс AMG",
    "5488": "AMG GT",
    "1645": "B-Класс",
    "5879": "C-Класс",
    "5880": "C-Класс AMG",
    "2526": "Citan",
    "747": "CL",
    "5881": "CL AMG",
    "2444": "CLA",
    "5882": "CLA AMG",
    "2409": "CLC",
    "751": "CLK",
    "5883": "CLK AMG",
    "1734": "CLS",
    "5954": "CLS AMG",
    "5884": "E-Класс",
    "10361": "E-Класс All-Terrain",
    "5885": "E-Класс AMG",
    "10343": "EQA",
    "10022": "EQC",
    "10229": "EQE",
    "10130": "EQS",
    "10271": "EQS SUV",
    "10332": "EQV",
    "774": "G-Класс",
    "5886": "G-Класс AMG",
    "1944": "GL-Класс",
    "5887": "GL-Класс AMG",
    "2537": "GLA",
    "5888": "GLA AMG",
    "10041": "GLB",
    "2718": "GLC",
    "5889": "GLC AMG",
    "5890": "GLC Coupe",
    "5891": "GLC Coupe AMG",
    "2675": "GLE",
    "5892": "GLE AMG",
    "5893": "GLE Coupe",
    "5894": "GLE Coupe AMG",
    "2040": "GLK",
    "5250": "GLS",
    "5895": "GLS AMG",
    "789": "M-Класс",
    "5904": "M-Класс AMG",
    "785": "Maybach",
    "10155": "Maybach GLS",
    "5798": "MB",
    "10217": "Metris",
    "1837": "R-Класс",
    "5896": "R-Класс AMG",
    "5897": "S-Класс",
    "5898": "S-Класс AMG",
    "811": "SL",
    "5899": "SL AMG",
    "5900": "SLC",
    "5901": "SLC AMG",
    "812": "SLK",
    "5902": "SLK AMG",
    "815": "SLR McLaren",
    "5761": "SLS AMG",
    "1910": "V-Класс",
    "818": "Vaneo",
    "820": "Viano",
    "821": "Vito",
    "10165": "W110",
    "5903": "X-класс"
}